okdata_resource_auth-0.1.4-nspkg.pth
okdata/resource_auth/__init__.py
okdata/resource_auth/authorizer.py
okdata_resource_auth-0.1.4.dist-info/METADATA
okdata_resource_auth-0.1.4.dist-info/WHEEL
okdata_resource_auth-0.1.4.dist-info/namespace_packages.txt
okdata_resource_auth-0.1.4.dist-info/top_level.txt
okdata_resource_auth-0.1.4.dist-info/RECORD
