Metadata-Version: 2.1
Name: okdata-resource-auth
Version: 0.1.4
Summary: Dataplatform resource authorizer
Home-page: https://github.com/oslokommune/okdata-resource-auth
Author: Oslo Origo
Author-email: dataplattform@oslo.kommune.no
License: UNKNOWN
Platform: UNKNOWN
Classifier: Development Status :: 3 - Alpha
Classifier: License :: OSI Approved :: MIT License
Classifier: Operating System :: OS Independent
Classifier: Programming Language :: Python :: 3
Requires-Dist: requests
